acf/__init__.py
acf/version.py
acf/core/__init__.py
acf/core/computation.py
acf/core/metrics.py
acf/core/preprocessing.py
acf/core/utils.py
acf/tests/__init__.py
acf/tests/test_computation.py
acf/tests/test_metrics.py
acf/tests/test_preprocessing.py
acf/tests/test_utils.py
acf-0.2.3.dist-info/LICENSE
acf-0.2.3.dist-info/METADATA
acf-0.2.3.dist-info/WHEEL
acf-0.2.3.dist-info/top_level.txt
acf-0.2.3.dist-info/RECORD
